{"name":"create account  page","id":"member-portal-signup-scenario;create-account--page","testSteps":[{"number":1,"description":"Then User can able to enter the data in create account page","duration":13162,"startTime":"2022-07-11T15:35:03.676085100+05:30[Asia/Calcutta]","result":"SUCCESS","precondition":false,"level":0}],"userStory":{"id":"member-portal-signup-scenario","storyName":"Member Portal Signup Scenario","displayName":"Member Portal Signup Scenario","path":"file:///C:/Users/Abhinav%20Kashyap/IdeaProjects/Member_Portal/src/main/resources/Feature/registration.feature","type":"feature"},"featureTag":{"name":"Feature/Member Portal Signup Scenario","type":"feature","displayName":"Feature/Member Portal Signup Scenario"},"title":"create account  page","description":"","startTime":"2022-07-11T15:35:03.671079500+05:30[Asia/Calcutta]","duration":13169,"projectKey":"","isManualTestingUpToDate":false,"manual":false,"testSource":"Cucumber","result":"SUCCESS"}